[{"username":"ali","password":"12345","email":"maktab@gmail.com","gender":"male","isLoggedIn":false},{"username":"reza","password":"4321","email":"maktab@yahoo.com","gender":"male","isLoggedIn":false},{"username":"hasan","password":"1234","email":"hasan@kilid.com","gender":"male","isLoggedIn":false},{"username":"h","password":"h","email":"h@h.com","gender":"h","isLoggedIn":true},{"username":"a","password":"a","email":"a@a.com","gender":"a","isLoggedIn":false},{"username":"hasan1","password":"1234","email":"hasan@kilid.com","gender":"male","isLoggedIn":false},{"username":"alireza12","password":"0000","email":"aliii@gmail.com","gender":"male","isLoggedIn":"false"}]